odoo/addons/delivery_line_sale_line_position/README.rst
odoo/addons/delivery_line_sale_line_position/__init__.py
odoo/addons/delivery_line_sale_line_position/__manifest__.py
odoo/addons/delivery_line_sale_line_position/i18n/delivery_line_sale_line_position.pot
odoo/addons/delivery_line_sale_line_position/i18n/it.po
odoo/addons/delivery_line_sale_line_position/models/__init__.py
odoo/addons/delivery_line_sale_line_position/models/stock_move.py
odoo/addons/delivery_line_sale_line_position/models/stock_move_line.py
odoo/addons/delivery_line_sale_line_position/readme/CONTRIBUTORS.md
odoo/addons/delivery_line_sale_line_position/readme/CREDITS.md
odoo/addons/delivery_line_sale_line_position/readme/DESCRIPTION.md
odoo/addons/delivery_line_sale_line_position/report/report_deliveryslip.xml
odoo/addons/delivery_line_sale_line_position/static/description/icon.png
odoo/addons/delivery_line_sale_line_position/static/description/index.html
odoo/addons/delivery_line_sale_line_position/views/stock_move.xml
odoo/addons/delivery_line_sale_line_position/views/stock_picking.xml
odoo_addon_delivery_line_sale_line_position-18.0.1.0.0.2.dist-info/METADATA
odoo_addon_delivery_line_sale_line_position-18.0.1.0.0.2.dist-info/WHEEL
odoo_addon_delivery_line_sale_line_position-18.0.1.0.0.2.dist-info/top_level.txt
odoo_addon_delivery_line_sale_line_position-18.0.1.0.0.2.dist-info/RECORD
