Metadata-Version: 2.1
Name: odoo-addon-delivery_line_sale_line_position
Version: 18.0.1.0.0.2
Requires-Python: >=3.10
Requires-Dist: odoo-addon-sale_order_line_position==18.0.*
Requires-Dist: odoo==18.0.*
Summary: Adds the sale line position to the delivery report lines
Home-page: https://github.com/OCA/stock-logistics-reporting
License: AGPL-3
Author: Camptocamp, Odoo Community Association (OCA)
Author-email: support@odoo-community.org
Classifier: Programming Language :: Python
Classifier: Framework :: Odoo
Classifier: Framework :: Odoo :: 18.0
Classifier: License :: OSI Approved :: GNU Affero General Public License v3
